setup.py
sky_pointer/__init__.py
sky_pointer/calc_pointer_errors.py
sky_pointer/coords.py
sky_pointer/pointer.py
sky_pointer/pointing_model.py
sky_pointer/protocol.py
sky_pointer/server.py
sky_pointer.egg-info/PKG-INFO
sky_pointer.egg-info/SOURCES.txt
sky_pointer.egg-info/dependency_links.txt
sky_pointer.egg-info/entry_points.txt
sky_pointer.egg-info/requires.txt
sky_pointer.egg-info/top_level.txt
sky_pointer/gui/__init__.py
sky_pointer/gui/bright_stars.py
sky_pointer/gui/calib_dlg.py
sky_pointer/gui/goto_dlg.py
sky_pointer/gui/main.py
sky_pointer/gui/main_dlg.py
sky_pointer/gui/parse_stars.py