Metadata-Version: 1.1
Name: sky-pointer
Version: 0.1
Summary: Software for controlling a motorized sky-pointing laser
Home-page: https://github.com/juanmb/SkyPointer
Author: Juan Menendez
Author-email: juanmb@gmail.com
License: MIT
Platform: any
Classifier: Development Status :: 2 - Pre-Alpha
Classifier: Intended Audience :: Education
Classifier: Intended Audience :: Science/Research
Classifier: License :: OSI Approved :: MIT License
Classifier: Operating System :: OS Independent
Classifier: Environment :: Console
Classifier: Programming Language :: Python
Classifier: Programming Language :: Python :: 2
Classifier: Programming Language :: Python :: 2.6
Classifier: Programming Language :: Python :: 2.7
